magic_cmd/__init__.py
magic_cmd/engine.py
magic_cmd/run_cmd.py
magic_cmd/script.py
magic_run_cmd-2.3.2.dist-info/LICENSE
magic_run_cmd-2.3.2.dist-info/METADATA
magic_run_cmd-2.3.2.dist-info/WHEEL
magic_run_cmd-2.3.2.dist-info/RECORD
