Metadata-Version: 2.1
Name: magic-run-cmd
Version: 2.3.2
Summary: Provides a clean way to express scripts such as shell or sql inside your python code..
License: Apache 2.0
Author: daniel davee
Author-email: daniel.v.davee@gmail.com
Requires-Python: >=3.10,<4.0
Classifier: License :: Other/Proprietary License
Classifier: Programming Language :: Python :: 3
Classifier: Programming Language :: Python :: 3.10
Classifier: Programming Language :: Python :: 3.11
Requires-Dist: icecream (>=2.1.3,<3.0.0)
Requires-Dist: paramiko (>=3.3.1,<4.0.0)
Requires-Dist: pysimplelog (>=4.0.0,<5.0.0)
